{
  "Epidermis (trichome/pavement)": [
    "819926",
    "835700",
    "836022",
    "820648",
    "836744",
    "829817",
    "843388",
    "818558",
    "836736",
    "822369",
    "829143"
  ],
  "Guard cells (stomata)": [
    "836874",
    "821416",
    "820898",
    "843083",
    "840012",
    "825507",
    "820954",
    "827327",
    "820938",
    "831897"
  ],
  "Mesophyll (photosynthesis)": [
    "820737",
    "821617",
    "844613",
    "826038",
    "825082",
    "820728",
    "820574",
    "843459",
    "827527",
    "840440",
    "824104",
    "827454",
    "825283",
    "819724"
  ],
  "Vascular tissue (phloem/xylem)": [
    "817200",
    "832562",
    "819453",
    "822951",
    "838088",
    "821980",
    "826645",
    "820517",
    "836624",
    "823754",
    "840023",
    "821711",
    "829143"
  ],
  "Trichomes (secretory)": [
    "828990",
    "839527",
    "845016",
    "836022",
    "838088",
    "829817",
    "836736",
    "829143",
    "819453"
  ],
  "Meristem (shoot apex)": [
    "834897",
    "837261",
    "832568",
    "833558",
    "835994",
    "835028",
    "833500",
    "816782",
    "843034",
    "822611",
    "820946"
  ],
  "Root (stele/endodermis)": [
    "836874",
    "821249",
    "832684",
    "836023",
    "825454",
    "826742",
    "839226",
    "835601",
    "836074",
    "821430",
    "820648",
    "828745"
  ],
  "Companion cells (phloem loading)": [
    "826645",
    "824104",
    "820517",
    "841786",
    "826742",
    "838069",
    "831670",
    "836337"
  ],
  "Immune response hubs": [
    "839939",
    "836283",
    "825606",
    "831459",
    "826329",
    "818052",
    "833413",
    "820898",
    "828785",
    "826285",
    "841786",
    "843083",
    "837897",
    "824283"
  ]
}